README.md
setup.py
utopy/__init__.py
utopy/utopy.py
utopy.egg-info/PKG-INFO
utopy.egg-info/SOURCES.txt
utopy.egg-info/dependency_links.txt
utopy.egg-info/entry_points.txt
utopy.egg-info/requires.txt
utopy.egg-info/top_level.txt