Metadata-Version: 1.0
Name: utopy
Version: 0.0.9
Summary: Curation bot for steem network
Home-page: http://github.com/emre/utopy
Author: emre yilmaz
Author-email: mail@emreyilmaz.me
License: MIT
Platform: UNKNOWN
